socialbladeclient/__init__.py
socialbladeclient-0.2.dist-info/DESCRIPTION.rst
socialbladeclient-0.2.dist-info/METADATA
socialbladeclient-0.2.dist-info/RECORD
socialbladeclient-0.2.dist-info/WHEEL
socialbladeclient-0.2.dist-info/metadata.json
socialbladeclient-0.2.dist-info/top_level.txt
