Metadata-Version: 2.0
Name: socialbladeclient
Version: 0.2
Summary: Social Blade Unofficial Client
Home-page: http://github.com/meauxt/socialbladeclient
Author: Mohamad Tarbin
Author-email: mhed.t91@gmail.com
License: MIT
Platform: UNKNOWN
Requires-Dist: lxml
Requires-Dist: requests
